calcium.py
setup.py
calcium.egg-info/PKG-INFO
calcium.egg-info/SOURCES.txt
calcium.egg-info/dependency_links.txt
calcium.egg-info/top_level.txt