Metadata-Version: 1.0
Name: calcium
Version: 0.1
Summary: Minimal interactive shell framework
Home-page: UNKNOWN
Author: URANO Ryoya
Author-email: urano.works.mail@gmail.com
License: MIT
Platform: UNKNOWN
